ai_monitor/BUSINESS_METRICS_IMPLEMENTATION.md
ai_monitor/TOKEN_FIX_DOCUMENTATION.md
ai_monitor/__init__.py
ai_monitor/advanced_metrics.py
ai_monitor/alerting.py
ai_monitor/async_core.py
ai_monitor/auto_integrate.py
ai_monitor/collectors.py
ai_monitor/config.py
ai_monitor/context_managers.py
ai_monitor/core.py
ai_monitor/cost_optimizer.py
ai_monitor/dashboard.py
ai_monitor/debug_azure_tokens.py
ai_monitor/decorators.py
ai_monitor/detectors.py
ai_monitor/exporters.py
ai_monitor/http_interceptor.py
ai_monitor/plug_and_play.py
ai_monitor/quality_analyzer.py
ai_monitor/security_metrics.py
ai_monitor/semantic_analyzer.py
ai_monitor/tracing.py
ai_monitor/utils.py
ai_monitor/version.py
ai_monitor-2.0.2.dist-info/licenses/LICENSE
ai_monitor-2.0.2.dist-info/METADATA
ai_monitor-2.0.2.dist-info/WHEEL
ai_monitor-2.0.2.dist-info/top_level.txt
ai_monitor-2.0.2.dist-info/RECORD
