Metadata-Version: 2.4
Name: ai-monitor
Version: 2.0.2
Summary: Ultra-lightweight AI monitoring - pure Python, no compilation required! Docker-friendly.
Home-page: https://github.com/Maersk-Global/ai-llm
Author: AI Monitor Team
Author-email: AI Monitor Team <ai-monitor@example.com>
Maintainer-email: AI Monitor Team <ai-monitor@example.com>
License: MIT
Project-URL: Homepage, https://github.com/Maersk-Global/ai-llm
Project-URL: Documentation, https://github.com/Maersk-Global/ai-llm#readme
Project-URL: Repository, https://github.com/Maersk-Global/ai-llm
Project-URL: Issues, https://github.com/Maersk-Global/ai-llm/issues
Project-URL: Changelog, https://github.com/Maersk-Global/ai-llm/blob/main/CHANGELOG.md
Keywords: ai,monitoring,llm,agent,observability,prometheus,opentelemetry,tracing,metrics,quality-analysis,hallucination-detection,drift-detection,dashboard,alerting,security,cost-optimization,async
Classifier: Development Status :: 5 - Production/Stable
Classifier: Intended Audience :: Developers
Classifier: License :: OSI Approved :: MIT License
Classifier: Operating System :: OS Independent
Classifier: Programming Language :: Python :: 3
Classifier: Programming Language :: Python :: 3.8
Classifier: Programming Language :: Python :: 3.9
Classifier: Programming Language :: Python :: 3.10
Classifier: Programming Language :: Python :: 3.11
Classifier: Programming Language :: Python :: 3.12
Classifier: Programming Language :: Python :: 3.13
Classifier: Topic :: Software Development :: Libraries :: Python Modules
Classifier: Topic :: System :: Monitoring
Classifier: Topic :: Scientific/Engineering :: Artificial Intelligence
Requires-Python: >=3.8
License-File: LICENSE
Requires-Dist: numpy>=1.20.0
Requires-Dist: requests>=2.25.0
Requires-Dist: httpx>=0.24.0
Requires-Dist: tiktoken>=0.5.0
Requires-Dist: psutil>=5.9.0
Provides-Extra: prometheus
Requires-Dist: prometheus-client>=0.15.0; extra == "prometheus"
Provides-Extra: tracing
Requires-Dist: opentelemetry-api>=1.22.0; extra == "tracing"
Requires-Dist: opentelemetry-sdk>=1.22.0; extra == "tracing"
Requires-Dist: opentelemetry-exporter-jaeger>=1.21.0; extra == "tracing"
Provides-Extra: jaeger
Requires-Dist: opentelemetry-api>=1.15.0; extra == "jaeger"
Requires-Dist: opentelemetry-sdk>=1.15.0; extra == "jaeger"
Requires-Dist: opentelemetry-exporter-jaeger>=1.15.0; extra == "jaeger"
Provides-Extra: dashboard
Requires-Dist: flask>=2.0.0; extra == "dashboard"
Requires-Dist: flask-cors>=3.0.0; extra == "dashboard"
Provides-Extra: semantic
Requires-Dist: sentence-transformers>=2.0.0; extra == "semantic"
Provides-Extra: system
Requires-Dist: psutil>=5.9.0; extra == "system"
Provides-Extra: all
Requires-Dist: prometheus-client>=0.15.0; extra == "all"
Requires-Dist: opentelemetry-api>=1.22.0; extra == "all"
Requires-Dist: opentelemetry-sdk>=1.22.0; extra == "all"
Requires-Dist: opentelemetry-exporter-jaeger>=1.21.0; extra == "all"
Requires-Dist: psutil>=5.9.0; extra == "all"
Requires-Dist: flask>=2.0.0; extra == "all"
Requires-Dist: flask-cors>=3.0.0; extra == "all"
Requires-Dist: sentence-transformers>=2.0.0; extra == "all"
Provides-Extra: dev
Requires-Dist: pytest>=7.0.0; extra == "dev"
Requires-Dist: pytest-cov>=4.0.0; extra == "dev"
Requires-Dist: black; extra == "dev"
Requires-Dist: flake8; extra == "dev"
Requires-Dist: mypy; extra == "dev"
Dynamic: author
Dynamic: home-page
Dynamic: license-file
Dynamic: requires-python
